smcphub_server/__init__.py
smcphub_server/__main__.py
smcphub_server/server.py
smcphub_server-0.0.9.dist-info/METADATA
smcphub_server-0.0.9.dist-info/WHEEL
smcphub_server-0.0.9.dist-info/entry_points.txt
smcphub_server-0.0.9.dist-info/top_level.txt
smcphub_server-0.0.9.dist-info/RECORD
