Metadata-Version: 2.4
Name: smcphub-server
Version: 0.0.9
Summary: A MCP server, by SMCPHUB
Author-email: SMCPHUB <smcphub@163.com>
License: MIT
Project-URL: Homepage, https://smcphub.com
Keywords: mcp,mcp server,smcphub,llm,automation
Classifier: Programming Language :: Python :: 3
Classifier: Programming Language :: Python :: 3.10
Classifier: License :: OSI Approved :: MIT License
Classifier: Operating System :: OS Independent
Classifier: Development Status :: 4 - Beta
Classifier: Intended Audience :: Developers
Classifier: Topic :: Software Development :: Libraries :: Python Modules
Requires-Python: >=3.10
Requires-Dist: httpx>=0.28.1
Requires-Dist: mcp[cli]>=1.6.0
Requires-Dist: python-dotenv>=1.1.0
